CHANGELOG
LICENSE
MANIFEST.in
README.rst
requirements.txt
setup.py
py_serverdensity.egg-info/PKG-INFO
py_serverdensity.egg-info/SOURCES.txt
py_serverdensity.egg-info/dependency_links.txt
py_serverdensity.egg-info/requires.txt
py_serverdensity.egg-info/top_level.txt
serverdensity/__init__.py
serverdensity/api/__init__.py
serverdensity/api/version.txt