Metadata-Version: 1.0
Name: py-serverdensity
Version: 1.0.12
Summary: Python ServerDensity.com API wrapper
Home-page: https://github.com/serverdensity/py-serverdensity
Author: Wes Mason
Author-email: wes@serverdensity.com
License: BSD
Platform: UNKNOWN
